fake_web_events/__init__.py
fake_web_events/config.template.yml
fake_web_events/event.py
fake_web_events/simulation.py
fake_web_events/user.py
fake_web_events/utils.py
fake_web_events-0.2.5.dist-info/METADATA
fake_web_events-0.2.5.dist-info/WHEEL
fake_web_events-0.2.5.dist-info/top_level.txt
fake_web_events-0.2.5.dist-info/RECORD
