Metadata-Version: 2.1
Name: fake-web-events
Version: 0.2.5
Summary: Generator of semi-random fake web events. 
Home-page: https://github.com/andresionek91/fake-web-events
Author: Andre Sionek
Author-email: andresionek91@gmail.com
License: MIT
Keywords: fake,web events,events
Platform: UNKNOWN
Classifier: Development Status :: 3 - Alpha
Classifier: Intended Audience :: Developers
Classifier: Topic :: Software Development :: Build Tools
Classifier: License :: OSI Approved :: MIT License
Classifier: Programming Language :: Python :: 3.7
